galiboo/__init__.py
galiboo-0.0.3.dist-info/DESCRIPTION.rst
galiboo-0.0.3.dist-info/METADATA
galiboo-0.0.3.dist-info/RECORD
galiboo-0.0.3.dist-info/WHEEL
galiboo-0.0.3.dist-info/metadata.json
galiboo-0.0.3.dist-info/top_level.txt
