Metadata-Version: 2.0
Name: galiboo
Version: 0.0.3
Summary: The official Python SDK for Galiboo's Music API.
Home-page: https://github.com/galiboo/galiboo-python
Author: Subhash
Author-email: subby@galiboo.com
License: UNKNOWN
Platform: UNKNOWN
Requires-Dist: requests
